needles/Code.py
needles/Kind.py
needles/Seq.py
needles/Sequences.py
needles/__init__.py
needles/__main__.py
needles/needles.py
needles/needles_pb2.py
needles/pbjson.py
needles-0.0.2.dist-info/DESCRIPTION.rst
needles-0.0.2.dist-info/METADATA
needles-0.0.2.dist-info/RECORD
needles-0.0.2.dist-info/WHEEL
needles-0.0.2.dist-info/entry_points.txt
needles-0.0.2.dist-info/metadata.json
needles-0.0.2.dist-info/top_level.txt
